datass/__init__.py
datass/dataframe/__init__.py
datass/dataframe/inspection.py
datass/exceptions/__init__.py
datass/series/__init__.py
datass/text/__init__.py
tests/__init__.py
tests/unit/__init__.py
datass-0.0.1.dev2.dist-info/LICENSE.txt
datass-0.0.1.dev2.dist-info/METADATA
datass-0.0.1.dev2.dist-info/WHEEL
datass-0.0.1.dev2.dist-info/top_level.txt
datass-0.0.1.dev2.dist-info/RECORD
