Metadata-Version: 2.1
Name: datass
Version: 0.0.1.dev2
Summary: Data Science Shortcuts. Package for lazy, or overwhelmed, data scientists
Home-page: https://github.com/htbrandao/datass
Author: Henrique Brandão
Author-email: brandao.t.henrique@gmail.com
License: MIT
Platform: UNKNOWN
Classifier: Programming Language :: Python :: 3
Classifier: License :: OSI Approved :: MIT License
Classifier: Operating System :: OS Independent
Requires-Python: >=3.8
